Metadata-Version: 2.1
Name: hellop
Version: 0.0.1
Summary: A hello world girly
Home-page: UNKNOWN
Author: rehmet
License: UNKNOWN
Platform: UNKNOWN
